<annotation verified="yes">
    <folder>Annotation</folder>
    <filename>raw180_20191118_161327.jpg</filename>
    <path>desks-PascalVOC-export/Annotations/raw180_20191118_161327.jpg</path>
    <source>
        <database>Unknown</database>
    </source>
    <size>
        <width>320</width>
        <height>239</height>
        <depth>3</depth>
    </size>
    <segmented>0</segmented>
    <object>
    <name>Dirtdesk</name>
    <pose>Unspecified</pose>
    <truncated>0</truncated>
    <difficult>0</difficult>
    <bndbox>
        <xmin>55.41772254911656</xmin>
        <ymin>24.575142273121635</ymin>
        <xmax>260.1097139125132</xmax>
        <ymax>190.92995586503025</ymax>
    </bndbox>
</object>
</annotation>
