<annotation verified="yes">
    <folder>Annotation</folder>
    <filename>raw90_20191118_155132.jpg</filename>
    <path>desks-PascalVOC-export/Annotations/raw90_20191118_155132.jpg</path>
    <source>
        <database>Unknown</database>
    </source>
    <size>
        <width>320</width>
        <height>239</height>
        <depth>3</depth>
    </size>
    <segmented>0</segmented>
    <object>
    <name>desk</name>
    <pose>Unspecified</pose>
    <truncated>0</truncated>
    <difficult>0</difficult>
    <bndbox>
        <xmin>21.39239991264504</xmin>
        <ymin>32.406779661016955</ymin>
        <xmax>312.2278450108781</xmax>
        <ymax>145.29040372169624</ymax>
    </bndbox>
</object>
</annotation>
